README.md
setup.py
vx/__init__.py
vx/main.py
vx.egg-info/PKG-INFO
vx.egg-info/SOURCES.txt
vx.egg-info/dependency_links.txt
vx.egg-info/top_level.txt