Metadata-Version: 2.1
Name: vx
Version: 0.1.3
Summary: Python implementation of the SBB genetic programming algorithm for classification tasks (library).
Home-page: https://pypi.org/project/vx/
Author: Mat Kallada
Author-email: matkallada@gmail.com
License: UNKNOWN
Keywords: machine learning,genetic programming,example
Platform: UNKNOWN
